odex/__init__.py
odex/condition.py
odex/container.py
odex/context.py
odex/index.py
odex/optimize.py
odex/parse.py
odex/plan.py
odex/set.py
odex/utils.py
odex-0.0.7.dist-info/LICENSE
odex-0.0.7.dist-info/METADATA
odex-0.0.7.dist-info/WHEEL
odex-0.0.7.dist-info/RECORD
