Metadata-Version: 2.1
Name: odex
Version: 0.0.7
Summary: Python object index for fast, declarative retrieval
Home-page: https://github.com/barakalon/odex
License: MIT
Author: Barak Alon
Requires-Python: >=3.7,<4.0
Classifier: License :: OSI Approved :: MIT License
Classifier: Programming Language :: Python :: 3
Classifier: Programming Language :: Python :: 3.7
Classifier: Programming Language :: Python :: 3.8
Classifier: Programming Language :: Python :: 3.9
Classifier: Programming Language :: Python :: 3.10
Classifier: Programming Language :: Python :: 3.11
Classifier: Programming Language :: Python :: 3.12
Requires-Dist: sortedcontainers
Requires-Dist: sqlglot
Requires-Dist: typing_extensions
